py.typed
codat_accounting/__init__.py
codat_accounting/_hooks/__init__.py
codat_accounting/_hooks/registration.py
codat_accounting/_hooks/sdkhooks.py
codat_accounting/_hooks/types.py
codat_accounting/account_transactions.py
codat_accounting/accounts.py
codat_accounting/bank_account_transactions.py
codat_accounting/bank_accounts.py
codat_accounting/basesdk.py
codat_accounting/bill_credit_notes.py
codat_accounting/bill_payments.py
codat_accounting/bills.py
codat_accounting/company_info.py
codat_accounting/credit_notes.py
codat_accounting/customers.py
codat_accounting/direct_costs.py
codat_accounting/direct_incomes.py
codat_accounting/httpclient.py
codat_accounting/invoices.py
codat_accounting/item_receipts.py
codat_accounting/items.py
codat_accounting/journal_entries.py
codat_accounting/journals.py
codat_accounting/models/errors/__init__.py
codat_accounting/models/errors/errormessage.py
codat_accounting/models/errors/sdkerror.py
codat_accounting/models/operations/__init__.py
codat_accounting/models/operations/create_account.py
codat_accounting/models/operations/create_bank_account.py
codat_accounting/models/operations/create_bank_transactions.py
codat_accounting/models/operations/create_bill.py
codat_accounting/models/operations/create_bill_credit_note.py
codat_accounting/models/operations/create_bill_payment.py
codat_accounting/models/operations/create_credit_note.py
codat_accounting/models/operations/create_customer.py
codat_accounting/models/operations/create_direct_cost.py
codat_accounting/models/operations/create_direct_income.py
codat_accounting/models/operations/create_invoice.py
codat_accounting/models/operations/create_item.py
codat_accounting/models/operations/create_journal.py
codat_accounting/models/operations/create_journal_entry.py
codat_accounting/models/operations/create_payment.py
codat_accounting/models/operations/create_purchase_order.py
codat_accounting/models/operations/create_supplier.py
codat_accounting/models/operations/create_transfer.py
codat_accounting-0.36.0.dist-info/METADATA
codat_accounting-0.36.0.dist-info/WHEEL
codat_accounting-0.36.0.dist-info/RECORD
